fastemriwaveforms_cuda12x-2.0.0.dist-info/WHEEL
fastemriwaveforms_cuda12x-2.0.0.dist-info/RECORD
fastemriwaveforms_cuda12x-2.0.0.dist-info/METADATA
fastemriwaveforms_cuda12x-2.0.0.dist-info/licenses/LICENSE
few_backend_cuda12x/pymatmul.cpython-39-x86_64-linux-gnu.so
few_backend_cuda12x/pyAmpInterp2D.cpython-39-x86_64-linux-gnu.so
few_backend_cuda12x/pyinterp.cpython-39-x86_64-linux-gnu.so
few_backend_cuda12x/git_version.py
few_backend_cuda12x/pyAAK.cpython-39-x86_64-linux-gnu.so
